src/__init__.py
src/cache.py
src/client.py
src/commands.py
src/config.py
src/leetcode.py
src/lru_cache.py
src/screen.py
src/system.py
src/data/__init__.py
src/data/company_frequency_ranking.py
src/data/company_tags.py
src/data/frequency.py
pyleetcode-3.0.5.dist-info/LICENSE
pyleetcode-3.0.5.dist-info/METADATA
pyleetcode-3.0.5.dist-info/WHEEL
pyleetcode-3.0.5.dist-info/entry_points.txt
pyleetcode-3.0.5.dist-info/top_level.txt
pyleetcode-3.0.5.dist-info/RECORD
