Metadata-Version: 2.1
Name: pyleetcode
Version: 3.0.5
Summary: UNKNOWN
Home-page: UNKNOWN
Author: UNKNOWN
Author-email: UNKNOWN
License: UNKNOWN
Platform: UNKNOWN
Requires-Dist: click
Requires-Dist: bs4
Requires-Dist: requests
Requires-Dist: colorama
Requires-Dist: pathlib
Requires-Dist: pytest
